staff/__init__.py
staff/__main__.py
staff/duration.py
staff/numerical.py
staff/pitch.py
staff/db/__init__.py
staff/db/db.py
staff/db/ensembles.py
staff/db/instruments.py
staff/db/staff.db
staff/db/packs/__init__.py
staff/db/packs/instruments/__init__.py
staff/db/packs/instruments/bbcso.py
staff/orchestration/__init__.py
staff/orchestration/ensemble.py
staff/orchestration/instrument.py
staff/orchestration/voicing.py
staff/patterns/__init__.py
staff/patterns/duration.py
staff/patterns/pattern.py
inegm.staff-0.2.4.dist-info/LICENSE
inegm.staff-0.2.4.dist-info/METADATA
inegm.staff-0.2.4.dist-info/WHEEL
inegm.staff-0.2.4.dist-info/entry_points.txt
inegm.staff-0.2.4.dist-info/top_level.txt
inegm.staff-0.2.4.dist-info/RECORD
